django_subui_tests-0.2.2.dist-info/DESCRIPTION.rst
django_subui_tests-0.2.2.dist-info/METADATA
django_subui_tests-0.2.2.dist-info/RECORD
django_subui_tests-0.2.2.dist-info/WHEEL
django_subui_tests-0.2.2.dist-info/metadata.json
django_subui_tests-0.2.2.dist-info/top_level.txt
subui/__init__.py
subui/step.py
subui/test_runner.py
subui/validators.py
