Metadata-Version: 2.0
Name: django-subui-tests
Version: 0.2.2
Summary: Framework to make workflow server integration test suites
Home-page: https://github.com/dealertrack/django-subui-tests
Author: Miroslav Shubernetskiy
Author-email: UNKNOWN
License: MIT
Keywords: django tests subui
Platform: UNKNOWN
Classifier: Intended Audience :: Developers
Classifier: Natural Language :: English
Classifier: License :: OSI Approved :: MIT License
Classifier: Programming Language :: Python
Classifier: Programming Language :: Python :: 2.7
Classifier: Programming Language :: Python :: 3
Classifier: Development Status :: 2 - Pre-Alpha
Requires-Dist: django
Requires-Dist: py-context
Requires-Dist: setuptools
Requires-Dist: six
